ahumai/__init__.py
ahumai-0.0.1.dist-info/METADATA
ahumai-0.0.1.dist-info/WHEEL
ahumai-0.0.1.dist-info/top_level.txt
ahumai-0.0.1.dist-info/RECORD
