Metadata-Version: 2.4
Name: ahumai
Version: 0.0.1
Summary: A simple package that prints happy holidays
Author: Your Name
Requires-Python: >=3.6
Dynamic: author
Dynamic: requires-python
Dynamic: summary
